setup.cfg
setup.py
pet/__init__.py
pet/bl.py
pet/cli.py
pet/exceptions.py
pet/file_templates.py
pet/utils.py
pety.egg-info/PKG-INFO
pety.egg-info/SOURCES.txt
pety.egg-info/dependency_links.txt
pety.egg-info/entry_points.txt
pety.egg-info/requires.txt
pety.egg-info/top_level.txt
tests/__init__.py
tests/conftest.py
tests/test_pet.py