Metadata-Version: 1.0
Name: pety
Version: 0.0.1
Summary: Project Environment Tool
Home-page: https://github.com/limebrains/pet
Author: LimeBrains
Author-email: mail@limebrains.com
License: UNKNOWN
Platform: UNKNOWN
